errorstack/__init__.py
errorstack/core.py
ErrorStack-0.0.1.dist-info/METADATA
ErrorStack-0.0.1.dist-info/WHEEL
ErrorStack-0.0.1.dist-info/top_level.txt
ErrorStack-0.0.1.dist-info/RECORD
