Metadata-Version: 2.1
Name: ErrorStack
Version: 0.0.1
Summary: Uncover solutions for python errors 
Author: Moses Kariuki
Author-email: musaspacecadet@gmail.com
License: UNKNOWN
Keywords: python,fix error,find bugs,error,solution
Platform: UNKNOWN
Classifier: Development Status :: 3 - Alpha
Classifier: Intended Audience :: Education
Classifier: Programming Language :: Python :: 2
Classifier: Programming Language :: Python :: 3
Classifier: Operating System :: MacOS :: MacOS X
Classifier: Operating System :: Microsoft :: Windows
